enbisysavm/__init__.py
enbisysavm/api_client.py
enbisysavm/configuration.py
enbisysavm/rest.py
enbisysavm/api/__init__.py
enbisysavm/api/addresses_api.py
enbisysavm/api/properties_api.py
enbisysavm/api/valuation_api.py
enbisysavm/models/__init__.py
enbisysavm/models/additional_features.py
enbisysavm/models/address.py
enbisysavm/models/built_form.py
enbisysavm/models/energy_efficiency.py
enbisysavm/models/energy_rating.py
enbisysavm/models/floor_level.py
enbisysavm/models/leasehold_or_freehold.py
enbisysavm/models/model_property.py
enbisysavm/models/new_or_resale.py
enbisysavm/models/price.py
enbisysavm/models/problem.py
enbisysavm/models/property_features.py
enbisysavm/models/property_type.py
enbisysavm/models/required_features.py
enbisysavm/models/response_property_features.py
enbisysavm/models/response_required_features.py
enbisysavm/models/roof_insulation.py
enbisysavm/models/roof_type.py
enbisysavm/models/valuation.py
enbisysavm/models/valuation_price_distribution.py
enbisysavm/models/wall_insulation.py
enbisysavm/models/wall_type.py
enbisysavm/models/window_glazing_type.py
swagger_client/__init__.py
swagger_client/api_client.py
swagger_client/configuration.py
swagger_client/rest.py
swagger_client/api/__init__.py
swagger_client/api/addresses_api.py
swagger_client/api/properties_api.py
swagger_client/api/valuation_api.py
swagger_client/models/__init__.py
swagger_client/models/additional_features.py
swagger_client/models/address.py
swagger_client/models/built_form.py
swagger_client/models/energy_efficiency.py
swagger_client/models/energy_rating.py
swagger_client/models/floor_level.py
swagger_client/models/leasehold_or_freehold.py
swagger_client/models/model_property.py
swagger_client/models/new_or_resale.py
swagger_client/models/price.py
swagger_client/models/problem.py
swagger_client/models/property_features.py
swagger_client/models/property_type.py
swagger_client/models/required_features.py
swagger_client/models/roof_insulation.py
enbisysavm-1.0.2.dist-info/LICENSE
enbisysavm-1.0.2.dist-info/METADATA
enbisysavm-1.0.2.dist-info/WHEEL
enbisysavm-1.0.2.dist-info/top_level.txt
enbisysavm-1.0.2.dist-info/RECORD
